metax/__init__.py
metax/matching.py
metax/prototypes.py
metax/version.py
metax/tests/__init__.py
metax/tests/test_matching.py
metax/tests/test_prototypes.py
metax-0.0.1.dist-info/LICENSE
metax-0.0.1.dist-info/METADATA
metax-0.0.1.dist-info/WHEEL
metax-0.0.1.dist-info/top_level.txt
metax-0.0.1.dist-info/RECORD
