Metadata-Version: 2.1
Name: metax
Version: 0.0.1
Summary: A collection of extensions for meta-learning in JAX
Home-page: https://github.com/tristandeleu/metax
Author: Tristan Deleu
Author-email: tristan.deleu@gmail.com
License: MIT
Keywords: meta-learning,jax,few-shot,few-shot learning
Platform: UNKNOWN
Requires-Dist: numpy
Requires-Dist: jax
Requires-Dist: jaxlib
